setup.py
geometry_lib/__init__.py
geometry_lib/shapes.py
geometry_lib/utils.py
geometry_lib.egg-info/PKG-INFO
geometry_lib.egg-info/SOURCES.txt
geometry_lib.egg-info/dependency_links.txt
geometry_lib.egg-info/top_level.txt